[
  {
    "id": 1568023012976,
    "status": "approved",
    "ssoID": "1567970311",
    "fullname": "OLANREWAJU AHMED OLAYINKA",
    "dob": "1993-07-17",
    "gender": "male",
    "passport_no": "1568022980950",
    "address": "5C AYO BABALOLA",
    "fileurl": "1568023012916.png",
    "publickey": "04965e4fb07a98fd3d81e08cee07b11548c1833d2fba55934086ac6fe807d244563d33f66c364fc9f358a75ccf7c343a3dae19674797a180f89d6f61074733638d",
    "userid": "5d7623076495e912209511d4"
  },
  {
    "id": 1568138451736,
    "status": "approved",
    "ssoID": "1568138013",
    "fullname": "OLANREWAJU AHMED OLAYINKA",
    "dob": "1993-04-04",
    "gender": "male",
    "passport_no": "1568138197480",
    "address": "3A SANNI STREET, SURULERE LAGOS, NIG",
    "fileurl": "1568138451486.png",
    "publickey": "04e42aee1c92893ef3c7e032298c751f63710ad6d22f6ee1377e66f0f51e10be690eb961f1666340815a88dc1f8e9fd7ef259f0233d90e0bb1fe60668e95e126b3",
    "userid": "5d77f443616fbf7e1426648b"
  }
]